nonconvexAG/__init__.py
nonconvexAG-1.1.6.dist-info/LICENSE
nonconvexAG-1.1.6.dist-info/METADATA
nonconvexAG-1.1.6.dist-info/WHEEL
nonconvexAG-1.1.6.dist-info/top_level.txt
nonconvexAG-1.1.6.dist-info/RECORD
