Metadata-Version: 2.1
Name: nonconvexAG
Version: 1.1.6
Summary: Implementation of accelerated gradient algorithm with strong rules for (high-dimensional) nonconvex sparse learning problems. Restarting, memory-mapping, and multiprocessing are now available. Developed by Kai Yang, [GPG Public key Fingerprint: CC02CF153594774CF956691492B2600D18170329](https://keys.openpgp.org/vks/v1/by-fingerprint/CC02CF153594774CF956691492B2600D18170329)
Author-email: Kai Yang <kai.yang2@mail.mcgill.ca>
License: GNU AFFERO GENERAL PUBLIC LICENSE
Project-URL: Homepage, https://github.com/Kaiyangshi-Ito/nonconvexAG
Project-URL: Bug Tracker, https://github.com/Kaiyangshi-Ito/nonconvexAG/issues
Classifier: Programming Language :: Python :: 3
Classifier: License :: OSI Approved :: GNU Affero General Public License v3 or later (AGPLv3+)
Classifier: Operating System :: OS Independent
Requires-Python: >=3.7
License-File: LICENSE
